qg_spider_sdk/__init__.py
qg_spider_sdk/client/__init__.py
qg_spider_sdk/client/bloom_filter_client.py
qg_spider_sdk/client/config_client.py
qg_spider_sdk/client/independ_crawl_client.py
qg_spider_sdk/client/web_man_client.py
qg_spider_sdk/client/website_sche_client.py
qg_spider_sdk/client/work_order_client.py
qg_spider_sdk/entity/__init__.py
qg_spider_sdk/entity/parse_result.py
qg_spider_sdk/entity/proxy.py
qg_spider_sdk/entity/proxy_old.py
qg_spider_sdk/entity/sys_res.py
qg_spider_sdk/entity/url_meta.py
qg_spider_sdk/entity/url_record.py
qg_spider_sdk/entity/website.py
qg_spider_sdk/enums/__init__.py
qg_spider_sdk/enums/download_enum.py
qg_spider_sdk/message/__init__.py
qg_spider_sdk/message/rabbit_mq.py
qg_spider_sdk/message/rabbit_mq_sync.py
qg_spider_sdk/pipe/__init__.py
qg_spider_sdk/pipe/independ_man.py
qg_spider_sdk/pipe/list_command.py
qg_spider_sdk/pipe/pool_command.py
qg_spider_sdk/pipe/proxy_man_old.py
qg_spider_sdk/pipe/script_command.py
qg_spider_sdk/pipe/sys_res_man.py
qg_spider_sdk/pipe/vpn_msg_man.py
qg_spider_sdk/pipe/website_man.py
qg_spider_sdk-5.2.9.dist-info/METADATA
qg_spider_sdk-5.2.9.dist-info/WHEEL
qg_spider_sdk-5.2.9.dist-info/top_level.txt
qg_spider_sdk-5.2.9.dist-info/RECORD
