Metadata-Version: 2.1
Name: qg-spider-sdk
Version: 5.2.9
Summary: 爬虫系统业务层封装
Home-page: http://192.168.117.144/cetc28/qg_spider_sdk
Author: zouwendi
Author-email: tz310200@gamil.com
Maintainer: zouwendi
Maintainer-email: tz310200@gamil.com
License: GPL3 License
Platform: all
Classifier: Development Status :: 4 - Beta
Classifier: Operating System :: OS Independent
Classifier: Intended Audience :: Developers
Classifier: Programming Language :: Python
Classifier: Programming Language :: Python :: Implementation
Classifier: Programming Language :: Python :: 3
Classifier: Programming Language :: Python :: 3.4
Classifier: Programming Language :: Python :: 3.5
Classifier: Programming Language :: Python :: 3.5
Classifier: Programming Language :: Python :: 3.6
Classifier: Programming Language :: Python :: 3.7
Classifier: Topic :: Software Development :: Libraries
Requires-Dist: qg-tool (>=0.0.2)
Requires-Dist: psutil (>=5.6.1)
Requires-Dist: aiohttp (>=3.5.4)
Requires-Dist: pika (>=0.13.0)
Requires-Dist: qg-struct (>=1.0.1)
Requires-Dist: typing (>=3.7.4.1)
Requires-Dist: setuptools (>=41.0.1)
Requires-Dist: pipreqs (>=0.4.9)
Requires-Dist: aio-pika (>=5.5.1)
